claudine/__init__.py
claudine/direct_test.py
claudine/exceptions.py
claudine/test_token_usage.py
claudine/token_tracking.py
claudine/tools.py
claudine/agent/__init__.py
claudine/agent/base.py
claudine/agent/cache.py
claudine/agent/messaging.py
claudine/api/__init__.py
claudine/api/client.py
claudine/api/constants.py
claudine/api/models.py
claudine/docs/ARCHITECTURE.md
claudine/docs/TOOLS.md
claudine/tokens/__init__.py
claudine/tokens/cache.py
claudine/tokens/models.py
claudine/tokens/pricing.py
claudine/tokens/tracking.py
claudine/tools/__init__.py
claudine/tools/callbacks.py
claudine/tools/manager.py
claudine/tools/schema.py
claudine/utils/__init__.py
claudine/utils/helpers.py
claudine-0.4.0.dist-info/METADATA
claudine-0.4.0.dist-info/WHEEL
claudine-0.4.0.dist-info/licenses/LICENSE
claudine-0.4.0.dist-info/RECORD
