Metadata-Version: 2.4
Name: claudine
Version: 0.4.0
Summary: Claudine AI agent
Author: Janito69
License: MIT
License-File: LICENSE
Requires-Python: >=3.8
Requires-Dist: anthropic>=0.18.0
Requires-Dist: typing-extensions>=4.0.0
Provides-Extra: dev
Requires-Dist: black>=23.0.0; extra == 'dev'
Requires-Dist: isort>=5.0.0; extra == 'dev'
Requires-Dist: pytest>=7.0.0; extra == 'dev'
